mobo/__init__.py
mobo/cluster.py
mobo/cluster_test.py
mobo/configuration.py
mobo/error.py
mobo/error_test.py
mobo/filter.py
mobo/filter_test.py
mobo/log.py
mobo/log_test.py
mobo/optimize.py
mobo/parameter.py
mobo/parameter_test.py
mobo/projection.py
mobo/projection_test.py
mobo/qoi.py
mobo-1.0.0.dist-info/LICENSE
mobo-1.0.0.dist-info/METADATA
mobo-1.0.0.dist-info/WHEEL
mobo-1.0.0.dist-info/top_level.txt
mobo-1.0.0.dist-info/RECORD
