Metadata-Version: 2.1
Name: mobo
Version: 1.0.0
Summary: A rational and extensible algorithm for solving multi-objective optimization problems
Home-page: https://github.com/seatonullberg/mobo
Author: Seaton Ullberg
Author-email: sullberg@ufl.edu
License: BSD 2-Clause License
Platform: UNKNOWN
